financetools/__init__.py
financetools/currency_utils.py
financetools/discount_utils.py
financetools/loan_utils.py
financetools/tax_utils.py
eldar_finance_matrix-0.1.0.dist-info/METADATA
eldar_finance_matrix-0.1.0.dist-info/WHEEL
eldar_finance_matrix-0.1.0.dist-info/top_level.txt
eldar_finance_matrix-0.1.0.dist-info/RECORD
