Metadata-Version: 2.4
Name: eldar_finance_matrix
Version: 0.1.0
Summary: Financial calculations utility library
Home-page: https://github.com/eldar/financetools
Author: Eldar Eliyev
Classifier: Programming Language :: Python :: 3
Classifier: License :: OSI Approved :: MIT License
Dynamic: author
Dynamic: classifier
Dynamic: description
Dynamic: description-content-type
Dynamic: home-page
Dynamic: summary
